lighter/__init__.py
lighter/callbacks/__init__.py
lighter/callbacks/base_writer.py
lighter/callbacks/csv_writer.py
lighter/callbacks/file_writer.py
lighter/callbacks/freezer.py
lighter/data.py
lighter/engine/__init__.py
lighter/engine/runner.py
lighter/model.py
lighter/utils/__init__.py
lighter/utils/data.py
lighter/utils/dynamic_imports.py
lighter/utils/logging.py
lighter/utils/misc.py
lighter/utils/types/__init__.py
lighter/utils/types/enums.py
lighter-0.1.0.dist-info/WHEEL
lighter-0.1.0.dist-info/entry_points.txt
lighter-0.1.0.dist-info/METADATA
lighter-0.1.0.dist-info/RECORD
