Metadata-Version: 2.4
Name: lighter
Version: 0.1.0
Summary: YAML-based automated rapid prototyping framework for deep learning experiments
Keywords: 
Author: Ibrahim Hadzic, Suraj Pai, Keno Bressem
Author-email: Ibrahim Hadzic <ibrahimhadzic45@gmail.com>, Suraj Pai <b.pai@maastrichtuniversity.nl>, Keno Bressem <kbressem@bwh.harvard.edu>
License-Expression: MIT
Classifier: Development Status :: 3 - Alpha
Classifier: Intended Audience :: Developers
Classifier: Operating System :: OS Independent
Classifier: Topic :: Software Development :: Libraries :: Python Modules
Classifier: License :: OSI Approved :: MIT License
Classifier: Programming Language :: Python :: 3
Classifier: Programming Language :: Python :: 3.10
Classifier: Programming Language :: Python :: 3.11
Classifier: Programming Language :: Python :: 3.12
Requires-Dist: torch>=2.1.2
Requires-Dist: pandas>=1.5.3
Requires-Dist: numpy<2.0.0
Requires-Dist: pytorch-lightning>=2.1.3
Requires-Dist: loguru>=0.6.0
Requires-Dist: torchmetrics>=1.2.0
Requires-Dist: tensorboard>=2.11.2
Requires-Dist: requests>=2.31.0
Requires-Dist: sparkwheel>=0.0.10
Requires-Dist: rich>=13.7.0
Requires-Dist: torchvision>=0.20.0
Requires-Dist: cloudpickle>=3.0.0
Requires-Python: >=3.10
Project-URL: Homepage, https://github.com/lighter/lighter
Project-URL: Repository, https://github.com/lighter/lighter
